main.py
zellij_mcp_server-0.1.0.dist-info/METADATA
zellij_mcp_server-0.1.0.dist-info/WHEEL
zellij_mcp_server-0.1.0.dist-info/top_level.txt
zellij_mcp_server-0.1.0.dist-info/RECORD
